pairio/__init__.py
pairio/cli.py
pairio/version.txt
pairio/client/__init__.py
pairio/client/submit_job.py
pairio/common/PairioJob.py
pairio/common/__init__.py
pairio/common/api_requests.py
pairio/common/pairio_types.py
pairio/compute_client/ComputeClientDaemon.py
pairio/compute_client/JobManager.py
pairio/compute_client/PubsubClient.py
pairio/compute_client/__init__.py
pairio/compute_client/_start_job.py
pairio/compute_client/register_compute_client.py
pairio/compute_client/start_compute_client.py
pairio/internal_job_monitoring/__init__.py
pairio/internal_job_monitoring/console_output_monitor.py
pairio/internal_job_monitoring/job_status_monitor.py
pairio/internal_job_monitoring/resource_utilization_monitor.py
pairio/internal_job_monitoring/utils.py
pairio/sdk/App.py
pairio/sdk/AppProcessor.py
pairio/sdk/InputFile.py
pairio/sdk/OutputFile.py
pairio/sdk/ProcessorBase.py
pairio/sdk/__init__.py
pairio/sdk/_load_spec_from_uri.py
pairio/sdk/_make_spec_file.py
pairio/sdk/_run_job_child_process.py
pairio/sdk/_run_job_parent_process.py
pairio/sdk/upload_additional_job_output.py
pairio-0.5.9.dist-info/METADATA
pairio-0.5.9.dist-info/WHEEL
pairio-0.5.9.dist-info/entry_points.txt
pairio-0.5.9.dist-info/top_level.txt
pairio-0.5.9.dist-info/RECORD
